LICENSE
README.md
pyproject.toml
setup.py
bulkboto3/__init__.py
bulkboto3/bulkboto3.py
bulkboto3/exceptions.py
bulkboto3/transfer_path.py
bulkboto3.egg-info/PKG-INFO
bulkboto3.egg-info/SOURCES.txt
bulkboto3.egg-info/dependency_links.txt
bulkboto3.egg-info/requires.txt
bulkboto3.egg-info/top_level.txt