Metadata-Version: 2.1
Name: bulkboto3
Version: 1.1.2
Summary: Python package for fast and parallel transferring a bulk of files to S3 based on boto3
Home-page: https://github.com/iamirmasoud/bulkboto3
Author: Amir Masoud Sefidian
Author-email: amir.masoud.sefidian@gmail.com
License: MIT
Keywords: Boto3,S3,Parallel,Multi-thread,Bulk,Boto,Bulk Boto,Bulk Boto3,Simple Storage Service,Minio,Amazon AWS S3,Python
Platform: UNKNOWN
Classifier: Development Status :: 5 - Production/Stable
Classifier: Intended Audience :: Developers
Classifier: Natural Language :: English
Classifier: Programming Language :: Python
Classifier: Programming Language :: Python :: 3
Classifier: Programming Language :: Python :: 3.6
Classifier: Programming Language :: Python :: 3.7
Classifier: Programming Language :: Python :: 3.8
Classifier: Programming Language :: Python :: 3.9
Classifier: Programming Language :: Python :: 3.10
Classifier: Operating System :: OS Independent
Classifier: License :: OSI Approved :: MIT License
Requires-Python: >=3.6.0
Provides-Extra: dev
License-File: LICENSE
